rltrace/LogLevel.py
rltrace/Trace.py
rltrace/UniqueRef.py
rltrace/__init__.py
rltrace-1.0.2.dist-info/LICENSE
rltrace-1.0.2.dist-info/METADATA
rltrace-1.0.2.dist-info/WHEEL
rltrace-1.0.2.dist-info/top_level.txt
rltrace-1.0.2.dist-info/zip-safe
rltrace-1.0.2.dist-info/RECORD
